pyexcel_xlsxr/__init__.py
pyexcel_xlsxr/_version.py
pyexcel_xlsxr/messy_xlsx.py
pyexcel_xlsxr/xlsxr.py
pyexcel_xlsxr-0.6.1.dist-info/LICENSE
pyexcel_xlsxr-0.6.1.dist-info/METADATA
pyexcel_xlsxr-0.6.1.dist-info/WHEEL
pyexcel_xlsxr-0.6.1.dist-info/top_level.txt
pyexcel_xlsxr-0.6.1.dist-info/RECORD
