Metadata-Version: 2.1
Name: pyexcel-xlsxr
Version: 0.6.1
Summary: Read xlsx file using partial xml
Home-page: https://github.com/pyexcel/pyexcel-xlsxr
Download-URL: https://github.com/pyexcel/pyexcel-xlsxr/archive/0.6.1.tar.gz
Author: C.W.
Author-email: info@pyexcel.org
License: New BSD
Keywords: python
Classifier: Topic :: Software Development :: Libraries
Classifier: Programming Language :: Python
Classifier: Intended Audience :: Developers
Classifier: Programming Language :: Python :: 3 :: Only
Classifier: Programming Language :: Python :: 3.6
Classifier: Programming Language :: Python :: 3.7
Classifier: Programming Language :: Python :: 3.8
Requires-Python: >=3.6
License-File: LICENSE
Requires-Dist: lxml>=3.4.4
Requires-Dist: pyexcel-io>=0.6.2
